odoo8_addon_purchase_add_product_supplierinfo-8.0.1.0.0-py2.7-nspkg.pth
odoo_addons/purchase_add_product_supplierinfo/purchase.py
odoo_addons/purchase_add_product_supplierinfo/purchase_view.xml
odoo_addons/purchase_add_product_supplierinfo/__openerp__.py
odoo_addons/purchase_add_product_supplierinfo/__init__.py
odoo_addons/purchase_add_product_supplierinfo/README.rst
odoo_addons/purchase_add_product_supplierinfo/i18n/fr.po
odoo_addons/purchase_add_product_supplierinfo/wizard/purchase_add_supplierinfo.py
odoo_addons/purchase_add_product_supplierinfo/wizard/__init__.py
odoo_addons/purchase_add_product_supplierinfo/wizard/purchase_add_supplierinfo.xml
odoo_addons/purchase_add_product_supplierinfo/tests/__init__.py
odoo_addons/purchase_add_product_supplierinfo/tests/test_purchase_add_product_supplierinfo.py
odoo_addons/purchase_add_product_supplierinfo/demo/product_demo.xml
odoo_addons/purchase_add_product_supplierinfo/demo/purchase_order_demo.xml
odoo_addons/purchase_add_product_supplierinfo/static/description/icon.png
odoo8_addon_purchase_add_product_supplierinfo-8.0.1.0.0.dist-info/top_level.txt
odoo8_addon_purchase_add_product_supplierinfo-8.0.1.0.0.dist-info/WHEEL
odoo8_addon_purchase_add_product_supplierinfo-8.0.1.0.0.dist-info/RECORD
odoo8_addon_purchase_add_product_supplierinfo-8.0.1.0.0.dist-info/metadata.json
odoo8_addon_purchase_add_product_supplierinfo-8.0.1.0.0.dist-info/DESCRIPTION.rst
odoo8_addon_purchase_add_product_supplierinfo-8.0.1.0.0.dist-info/METADATA
odoo8_addon_purchase_add_product_supplierinfo-8.0.1.0.0.dist-info/namespace_packages.txt
