Metadata-Version: 2.0
Name: odoo8-addon-purchase-add-product-supplierinfo
Version: 8.0.1.0.0
Summary: In the purchase order, allow automatically complete with partner, the supplierinfo list for all products which are not related to this supplier
Home-page: http://akretion.com
Author: UNKNOWN
Author-email: UNKNOWN
License: AGPL-3
Platform: UNKNOWN
Requires-Dist: odoo (<9.0a,>=8.0a)
Requires-Dist: odoo8-addon-product-variant-supplierinfo
Classifier: Programming Language :: Python :: 2.7
Classifier: Framework :: Odoo
Classifier: License :: OSI Approved :: GNU Affero General Public License v3
